README.md
setup.cfg
setup.py
tm_v71_tools.egg-info/PKG-INFO
tm_v71_tools.egg-info/SOURCES.txt
tm_v71_tools.egg-info/dependency_links.txt
tm_v71_tools.egg-info/entry_points.txt
tm_v71_tools.egg-info/requires.txt
tm_v71_tools.egg-info/top_level.txt
tmv71/__init__.py
tmv71/api.py
tmv71/cli.py
tmv71/memory.py
tmv71/schema.py