Metadata-Version: 2.1
Name: tm-v71-tools
Version: 3.0.1
Summary: Tool for controlling a Kenwood TM-V71 radio
Home-page: https://github.com/larsks/tm-v71-tools
Author: Lars Kellogg-Stedman
Author-email: lars@oddbit.com
License: UNKNOWN
Platform: UNKNOWN
